qingping_sdk/__init__.py
qingping_sdk/client.py
qingping_sdk/connection.py
qingping_sdk/exceptions.py
qingping_sdk/typing.py
qingping_sdk/utils.py
qingping_sdk-0.0.2.dist-info/METADATA
qingping_sdk-0.0.2.dist-info/WHEEL
qingping_sdk-0.0.2.dist-info/top_level.txt
qingping_sdk-0.0.2.dist-info/RECORD
