Metadata-Version: 2.1
Name: qingping_sdk
Version: 0.0.2
Summary: qingping sdk for python in asyncio with binary protocol parser
Home-page: https://github.com/synodriver/qingping_sdk
Author: synodriver
Author-email: diguohuangjiajinweijun@gmail.com
Maintainer: v-vinson
License: GPLv3
Keywords: asyncio,qingping,cleargrass
Classifier: Development Status :: 3 - Alpha
Classifier: Framework :: AsyncIO
Classifier: Operating System :: OS Independent
Classifier: License :: OSI Approved :: GNU General Public License v3 (GPLv3)
Classifier: Programming Language :: Python
Classifier: Programming Language :: Python :: 3.8
Classifier: Programming Language :: Python :: 3.9
Classifier: Programming Language :: Python :: 3.10
Classifier: Programming Language :: Python :: 3.11
Classifier: Programming Language :: Python :: 3.12
Classifier: Programming Language :: Python :: 3.13
Classifier: Programming Language :: Python :: Implementation :: CPython
Requires-Python: >=3.8
Requires-Dist: aiohttp
Requires-Dist: crcmod-plus
